topsis_saanchi_102303323/__init__.py
topsis_saanchi_102303323/topsis.py
topsis_saanchi_102303323-0.0.5.dist-info/licenses/LICENSE
topsis_saanchi_102303323-0.0.5.dist-info/METADATA
topsis_saanchi_102303323-0.0.5.dist-info/WHEEL
topsis_saanchi_102303323-0.0.5.dist-info/entry_points.txt
topsis_saanchi_102303323-0.0.5.dist-info/top_level.txt
topsis_saanchi_102303323-0.0.5.dist-info/RECORD
