Metadata-Version: 2.4
Name: Topsis_Saanchi_102303323
Version: 0.0.5
Summary: A Python package for TOPSIS method
Author: Saanchi
Author-email: saanchigupta230@gmail.com
Requires-Python: >=3.7
License-File: LICENSE
Requires-Dist: numpy
Requires-Dist: pandas
Dynamic: author
Dynamic: author-email
Dynamic: description
Dynamic: description-content-type
Dynamic: license-file
Dynamic: requires-dist
Dynamic: requires-python
Dynamic: summary
